nbgitpuller/__init__.py
nbgitpuller/_compat.py
nbgitpuller/handlers.py
nbgitpuller/pull.py
nbgitpuller/version.py
nbgitpuller/etc/jupyter_notebook_config.d/nbgitpuller.json
nbgitpuller/etc/jupyter_server_config.d/nbgitpuller.json
nbgitpuller/static/dist/bundle.js
nbgitpuller/static/dist/bundle.js.map
nbgitpuller/static/js/gitsync.js
nbgitpuller/static/js/gitsyncview.js
nbgitpuller/static/js/index.js
nbgitpuller/templates/page.html
nbgitpuller/templates/status.html
nbgitpuller-1.2.2.data/data/etc/jupyter/jupyter_notebook_config.d/nbgitpuller.json
nbgitpuller-1.2.2.data/data/etc/jupyter/jupyter_server_config.d/nbgitpuller.json
nbgitpuller-1.2.2.dist-info/LICENSE
nbgitpuller-1.2.2.dist-info/METADATA
nbgitpuller-1.2.2.dist-info/WHEEL
nbgitpuller-1.2.2.dist-info/entry_points.txt
nbgitpuller-1.2.2.dist-info/top_level.txt
nbgitpuller-1.2.2.dist-info/RECORD
