Metadata-Version: 2.2
Name: nbgitpuller
Version: 1.2.2
Summary: Jupyter Extension to do one-way synchronization of git repositories
Home-page: https://github.com/jupyterhub/nbgitpuller
Author: Peter Veerman, YuviPanda
Author-email: peterkangveerman@gmail.com
License: 3-clause BSD
Platform: any
Classifier: Development Status :: 5 - Production/Stable
Classifier: License :: OSI Approved :: BSD License
Classifier: Operating System :: POSIX
Classifier: Operating System :: MacOS
Classifier: Operating System :: Unix
Classifier: Programming Language :: Python :: 3
Classifier: Topic :: Software Development :: Libraries :: Python Modules
License-File: LICENSE
Requires-Dist: jupyter_server>=1.10.1
Requires-Dist: tornado
Dynamic: author
Dynamic: author-email
Dynamic: classifier
Dynamic: description
Dynamic: description-content-type
Dynamic: home-page
Dynamic: license
Dynamic: platform
Dynamic: requires-dist
Dynamic: summary
